hopeit_agents/agent_toolkit/__init__.py
hopeit_agents/agent_toolkit/py.typed
hopeit_agents/agent_toolkit/settings.py
hopeit_agents/agent_toolkit/agents/__init__.py
hopeit_agents/agent_toolkit/agents/agent_config.py
hopeit_agents/agent_toolkit/agents/prompts.py
hopeit_agents/agent_toolkit/agents/py.typed
hopeit_agents/agent_toolkit/app/__init__.py
hopeit_agents/agent_toolkit/app/py.typed
hopeit_agents/agent_toolkit/app/steps/__init__.py
hopeit_agents/agent_toolkit/app/steps/agent_loop.py
hopeit_agents/agent_toolkit/app/steps/py.typed
hopeit_agents/agent_toolkit/mcp/__init__.py
hopeit_agents/agent_toolkit/mcp/agent_tools.py
hopeit_agents/agent_toolkit/mcp/py.typed
hopeit_agents_agent_toolkit-0.1.0b2.dist-info/METADATA
hopeit_agents_agent_toolkit-0.1.0b2.dist-info/WHEEL
hopeit_agents_agent_toolkit-0.1.0b2.dist-info/top_level.txt
hopeit_agents_agent_toolkit-0.1.0b2.dist-info/RECORD
